isystem/__init__.py
isystem/_connect.pyd
isystem/arraychart.py
isystem/blue.css
isystem/connect.py
isystem/diagutils.py
isystem/flamegraph.py
isystem/flowchart.py
isystem/gray.css
isystem/icutils.py
isystem/islAPI.py
isystem/isysCvrgToCobertura.xslt
isystem/isystemTestReport.xslt
isystem/itest.py
isystem/path_converter.py
isystem/seqAndCallDiag.py
isystem/staticCallGraph.py
isystem_connect-9.21.367.3.dist-info/licenses/LICENSE.txt
isystem_connect-9.21.367.3.dist-info/licenses/license_samples.py
isystem_connect-9.21.367.3.dist-info/METADATA
isystem_connect-9.21.367.3.dist-info/WHEEL
isystem_connect-9.21.367.3.dist-info/top_level.txt
isystem_connect-9.21.367.3.dist-info/RECORD
