Metadata-Version: 2.4
Name: isystem.connect
Version: 9.21.367.3
Summary: isystem.connect for Python
Author: TASKING Germany GmbH
License: Other/Proprietary License
Project-URL: Homepage, http://www.isystem.com/downloads/winIDEA/SDK/iSYSTEM.Python.SDK/documentation/isystem-connect-api/index.html
Project-URL: Support, https://support.tasking.com/T
Keywords: debugging,testing,embedded,software
Classifier: Development Status :: 5 - Production/Stable
Classifier: Intended Audience :: Developers
Classifier: Topic :: Software Development :: Debuggers
Classifier: Topic :: Software Development :: Testing
Classifier: Operating System :: Microsoft :: Windows
Classifier: Operating System :: POSIX :: Linux
Classifier: License :: Other/Proprietary License
Classifier: Programming Language :: Python :: 3.8
Classifier: Programming Language :: Python :: 3.9
Classifier: Programming Language :: Python :: 3.10
Classifier: Programming Language :: Python :: 3.11
Classifier: Programming Language :: Python :: 3.12
Requires-Python: >=2.7
License-File: LICENSE.txt
License-File: license_samples.py
Dynamic: license-file
